[
    {
        "name": "Холбоо Барих",
        "id": 87234892
    },
    {
        "name": "Бидний тухай",
        "id": 93840938
    },
    {
        "name": "Мэдээ",
        "id": 69850968
    },
    {
        "name": "Resources",
        "id": 49859090
    },
    {
        "name": "Newsletters",
        "id": 267153268
    },
    {
        "name": "Events",
        "id": 94859045
    },
    {
        "name": "Хамтрагч",
        "id": 90458003
    },
    {
        "name": "Санал хүсэлт",
        "id": 20398895
    },
    {
        "name": "Privacy",
        "id": 837459950
    },
    {
        "name": "Terms & Conditions",
        "id": 1111111
    },
    {
        "name": "Subscribe",
        "id": 39834943
    },
    {
        "name": "Project Developers",
        "id": 38405987
    }
]